Metadata-Version: 2.1
Name: pigpio-dht
Version: 0.3.6
Summary: DHT11 & DHT22 Temperature and Humidity Sensor using pigpio
Home-page: https://github.com/garyns/pigpio-dht
License: LGPL3
Download-URL: https://github.com/garyns/pigpio-dht/archive/master.zip
Keywords: DHT11,DHT22,pigpio,Raspberry Pi,RaspberryPi
Platform: UNKNOWN
Classifier: Development Status :: 4 - Beta
Classifier: Intended Audience :: Developers
Classifier: Topic :: Software Development :: Libraries :: Python Modules
Classifier: License :: OSI Approved :: GNU General Public License v3 (GPLv3)
Classifier: Programming Language :: Python :: 3
Classifier: Programming Language :: Python :: 3.4
Classifier: Programming Language :: Python :: 3.5
Classifier: Programming Language :: Python :: 3.6
